cmux/__init__.py
cmux-0.1.0.dist-info/METADATA
cmux-0.1.0.dist-info/WHEEL
cmux-0.1.0.dist-info/top_level.txt
cmux-0.1.0.dist-info/RECORD
