Metadata-Version: 2.4
Name: cmux
Version: 0.1.0
Summary: A multiplexer tool
Home-page: https://github.com/lawrencechen/cmux
Author: Lawrence Chen
Author-email: lawrence@example.com
Classifier: Programming Language :: Python :: 3
Classifier: License :: OSI Approved :: MIT License
Classifier: Operating System :: OS Independent
Requires-Python: >=3.6
Dynamic: author
Dynamic: author-email
Dynamic: classifier
Dynamic: description
Dynamic: description-content-type
Dynamic: home-page
Dynamic: requires-python
Dynamic: summary
